MANIFEST.in
NEWS.txt
README.rst
setup.py
src/projector/__init__.py
src/projector.egg-info/PKG-INFO
src/projector.egg-info/SOURCES.txt
src/projector.egg-info/dependency_links.txt
src/projector.egg-info/entry_points.txt
src/projector.egg-info/not-zip-safe
src/projector.egg-info/top_level.txt