Metadata-Version: 1.0
Name: projector
Version: 0.1.1
Summary: SDK for Projector, a developer platform for mobile push notifications
Home-page: https://www.projector.com
Author: Aaron Gotwalt
Author-email: aaron@projector.com
License: MIT
Keywords: push-notifications projector apns gcm
Platform: UNKNOWN
